pep440/__init__.py
pep440/__main__.py
pep440/core.py
pep440/py.typed
pep440-0.1.1.dist-info/LICENSE
pep440-0.1.1.dist-info/WHEEL
pep440-0.1.1.dist-info/METADATA
pep440-0.1.1.dist-info/RECORD
