Metadata-Version: 2.1
Name: pep440
Version: 0.1.1
Summary: A simple package with utils to check whether versions number match PEP 440.
Home-page: https://github.com/Carreau/pep440
Author: Matthias Bussonnier
Author-email: bussonniermatthias@gmail.com
Classifier: License :: OSI Approved :: MIT License
